ait/gui/__init__.py
ait/gui/bin/__init__.py
ait/gui/bin/ait_example.py
ait/gui/openmct_adapter/ait_integration.js
ait/gui/openmct_adapter/example_ait_telem_fetch.js
ait/gui/static/.babelrc
ait/gui/static/.jshintrc
ait/gui/static/build/0292d248d009b01cf97cefdfa39c3cf3.svg
ait/gui/static/build/0a0697bc7da165088daf16abaa2b0b96.eot
ait/gui/static/build/448c34a56d699c29117adc64c43affeb.woff2
ait/gui/static/build/89889688147bd7575d6327160d64e760.svg
ait/gui/static/build/ait.bundle.css
ait/gui/static/build/ait.bundle.js
ait/gui/static/build/e18bbf611f2a2e43afc071aa2f4e1512.ttf
ait/gui/static/build/f4769f9bdb7466be65088239c12046d1.eot
ait/gui/static/build/fa2772327f55d8198301fdb8bcfc8158.woff
ait/gui/static/css/ait/gui/Clock.css
ait/gui/static/css/ait/gui/Command.css
ait/gui/static/css/ait/gui/Field.css
ait/gui/static/css/ait/gui/Messages.css
ait/gui/static/css/ait/gui/Playback.css
ait/gui/static/css/ait/gui/Plot.css
ait/gui/static/css/ait/gui/Query.css
ait/gui/static/css/ait/gui/Script.css
ait/gui/static/css/ait/gui/Search.css
ait/gui/static/css/ait/gui/Sequence.css
ait/gui/static/css/ait/gui/Status.css
ait/gui/static/css/ait/gui/TabSet.css
ait/gui/static/css/typeahead.css
ait/gui/static/fonts/FontAwesome.otf
ait/gui/static/fonts/fontawesome-webfont.eot
ait/gui/static/fonts/fontawesome-webfont.svg
ait/gui/static/fonts/fontawesome-webfont.ttf
ait/gui/static/fonts/fontawesome-webfont.woff
ait/gui/static/fonts/fontawesome-webfont.woff2
ait/gui/static/fonts/glyphicons-halflings-regular.eot
ait/gui/static/fonts/glyphicons-halflings-regular.svg
ait/gui/static/fonts/glyphicons-halflings-regular.ttf
ait/gui/static/fonts/glyphicons-halflings-regular.woff
ait/gui/static/index.css
ait/gui/static/index.html
ait/gui/static/index.js
ait/gui/static/js/ait/cmd.js
ait/gui/static/js/ait/dtype.js
ait/gui/static/js/ait/events.js
ait/gui/static/js/ait/evr.js
ait/gui/static/js/ait/format.js
ait/gui/static/js/ait/gui/Clock.js
ait/gui/static/js/ait/gui/Command.js
ait_gui-2.4.1.dist-info/LICENSE.txt
ait_gui-2.4.1.dist-info/METADATA
ait_gui-2.4.1.dist-info/WHEEL
ait_gui-2.4.1.dist-info/entry_points.txt
ait_gui-2.4.1.dist-info/RECORD
