Metadata-Version: 2.1
Name: ait-gui
Version: 2.4.1
Summary: A framework for building a custom website for realtime telemetry monitoring, commanding, and other MOS operations, built atop the AIT Core libraries.
Home-page: https://github.com/NASA-AMMOS/AIT-GUI
License: MIT
Author: AMMOS Instrument Toolkit Development Team
Author-email: ait-pmc@googlegroups.com
Requires-Python: >=3.7,<3.11
Classifier: License :: OSI Approved :: MIT License
Classifier: Programming Language :: Python :: 3
Classifier: Programming Language :: Python :: 3.7
Classifier: Programming Language :: Python :: 3.8
Classifier: Programming Language :: Python :: 3.9
Classifier: Programming Language :: Python :: 3.10
Requires-Dist: ait-core (>=2.5.0)
Requires-Dist: greenlet (==1.1.3)
Project-URL: Documentation, https://ait-gui.readthedocs.io/en/latest
Project-URL: Repository, https://github.com/NASA-AMMOS/AIT-GUI
